distributions234/Binomialdistribution.py
distributions234/Gaussiandistribution.py
distributions234/Generaldistribution.py
distributions234/__init__.py
distributions234-0.1.dist-info/DESCRIPTION.rst
distributions234-0.1.dist-info/METADATA
distributions234-0.1.dist-info/RECORD
distributions234-0.1.dist-info/WHEEL
distributions234-0.1.dist-info/metadata.json
distributions234-0.1.dist-info/top_level.txt
